odoo/addons/sale_payment_mgmt/README.rst
odoo/addons/sale_payment_mgmt/__init__.py
odoo/addons/sale_payment_mgmt/__manifest__.py
odoo/addons/sale_payment_mgmt/i18n/es.po
odoo/addons/sale_payment_mgmt/i18n/sale_payment_mgmt.pot
odoo/addons/sale_payment_mgmt/models/__init__.py
odoo/addons/sale_payment_mgmt/models/account_payment.py
odoo/addons/sale_payment_mgmt/readme/CONTRIBUTORS.rst
odoo/addons/sale_payment_mgmt/readme/DESCRIPTION.rst
odoo/addons/sale_payment_mgmt/readme/USAGE
odoo/addons/sale_payment_mgmt/security/ir.model.access.csv
odoo/addons/sale_payment_mgmt/security/security.xml
odoo/addons/sale_payment_mgmt/static/description/icon.png
odoo/addons/sale_payment_mgmt/static/description/index.html
odoo/addons/sale_payment_mgmt/static/description/payment_menu.png
odoo/addons/sale_payment_mgmt/tests/__init__.py
odoo/addons/sale_payment_mgmt/tests/test_access_rights.py
odoo/addons/sale_payment_mgmt/views/account_move_view.xml
odoo/addons/sale_payment_mgmt/views/account_payment_view.xml
odoo13_addon_sale_payment_mgmt-13.0.1.0.1.dist-info/METADATA
odoo13_addon_sale_payment_mgmt-13.0.1.0.1.dist-info/WHEEL
odoo13_addon_sale_payment_mgmt-13.0.1.0.1.dist-info/top_level.txt
odoo13_addon_sale_payment_mgmt-13.0.1.0.1.dist-info/RECORD
